{
  "contatos": [
    {
      "id": 1,
      "nome": "Lucas",
      "telefone": "9999-6666",
      "data": "new Date()",
      "cor": "blue",
      "operadora": {
        "nome": "Oi",
        "codigo": 14,
        "categoria": "Celular"
      }
    },
    {
      "id": 2,
      "nome": "Pedro",
      "telefone": "9999-7777",
      "data": "new Date()",
      "cor": "red",
      "operadora": {
        "nome": "Vivo",
        "codigo": 15,
        "categoria": "Celular"
      }
    },
    {
      "id": 3,
      "nome": "Carlos",
      "telefone": "9999-8888",
      "data": "new Date()",
      "cor": "green",
      "operadora": {
        "nome": "Tim",
        "codigo": 41,
        "categoria": "Celular"
      }
    },
    {
      "nome": "Lucas de Santana Rodrigues",
      "telefone": "99999-9999",
      "operadora": {
        "id": 5,
        "nome": "Embratel",
        "codigo": 21,
        "categoria": "Fixo",
        "preco": 1
      },
      "data": "2022-04-17T15:47:38.447Z",
      "id": 4
    },
    {
      "nome": "Teste da Silva",
      "telefone": "9999-9988",
      "operadora": {
        "id": 2,
        "nome": "Vivo",
        "codigo": 15,
        "categoria": "Celular",
        "preco": 1
      },
      "data": "2022-04-17T15:51:16.002Z",
      "id": 5
    },
    {
      "nome": "Teste da silva hash",
      "telefone": "99999-9999",
      "data": "2022-04-23T18:01:20.902Z",
      "operadora": {
        "id": 5,
        "nome": "Embratel",
        "codigo": 21,
        "categoria": "Fixo",
        "preco": 1
      },
      "serial": "4>0EAB.>0Y]L,8$C\\TGA",
      "id": 6
    }
  ],
  "operadoras": [
    {
      "id": 1,
      "nome": "Oi",
      "codigo": 14,
      "categoria": "Celular",
      "preco": 1
    },
    {
      "id": 2,
      "nome": "Vivo",
      "codigo": 15,
      "categoria": "Celular",
      "preco": 1
    },
    {
      "id": 3,
      "nome": "Tim",
      "codigo": 41,
      "categoria": "Celular",
      "preco": 1
    },
    {
      "id": 4,
      "nome": "GVT",
      "codigo": 25,
      "categoria": "Fixo",
      "preco": 1
    },
    {
      "id": 5,
      "nome": "Embratel",
      "codigo": 21,
      "categoria": "Fixo",
      "preco": 1
    }
  ]
}